GAME/controladora_jogo.vhd
library ieee;
use ieee.std_logic_1164.all;
use ieee.numeric_std.all;

entity controladora_jogo is
	port(
		--entradas
		ctrl_CLK : in std_logic;
		ctrl_FINISH : in std_logic;
		ctrl_START : in std_logic;
		ctrl_Q0_MOEDA : in std_logic;
		ctrl_COLLECTED : in std_logic;
		ctrl_Q0_OBST : in std_logic;
		ctrl_ENDED : in std_logic;
		ctrl_PLAYER : in std_logic;
		ctrl_FRAME_TIMER : in std_logic;
		ctrl_RESULT : in std_logic_vector(2 downto 0);
		
		--saidas
		ctrl_LFSR_SHFT : out std_logic;
		ctrl_CNT_MOEDA1: out std_logic;
		ctrl_CNT_MOEDA2 : out std_logic;
		ctrl_RMV_MOEDA : out std_logic;
		ctrl_RMV_OBST : out std_logic;
		ctrl_SET_PLAYER : out std_logic;
		ctrl_CLR_MOEDA : out std_logic;
		ctrl_CLR_PLAYER : out std_logic;
		ctrl_CLR_TIMER : out std_logic;
		ctrl_CLR_START : out std_logic;
		ctrl_RENDER : out std_logic;
		ctrl_CMD : out std_logic_vector(2 downto 0)
		);
end controladora_jogo;

architecture arch of controladora_jogo is
	type estado is (s0,s1,s2,s3,s4,s5,s6,s7,sa8,s8,s9,
						 s10,s11,s12,s13,s14,s15,s16,s17,s18,s19);
	signal estado_atual,prox_estado : estado := s0;
begin
	sequencial:
	process(ctrl_CLK) is
	begin
		if rising_edge(ctrl_CLK) then
			estado_atual <= prox_estado;
		end if;
	end process;
	
	logico:
	process(ctrl_CLK,ctrl_FINISH,ctrl_START,estado_atual) is
	begin
		case estado_atual is
		
			when s0 => -- ESPERA O LCD INICIALIZAR
				ctrl_LFSR_SHFT <= '0';
				ctrl_CNT_MOEDA1 <= '0';
				ctrl_CNT_MOEDA2 <= '0';
				ctrl_RMV_MOEDA <= '0';
				ctrl_RMV_OBST <= '0';
				ctrl_SET_PLAYER <= '0';
				ctrl_CLR_MOEDA <= '0';
				ctrl_CLR_PLAYER <= '0';
				ctrl_CLR_TIMER <= '0';
				ctrl_CLR_START <= '0';
				ctrl_RENDER <= '0';
				ctrl_CMD <= "000";
				
				if ctrl_FINISH = '1' then
					prox_estado <= s1;
				else 
					prox_estado <= s0;
				end if;
			
			when s1 => --ESPERA APERTAR START
				ctrl_LFSR_SHFT <= '0';
				ctrl_CNT_MOEDA1 <= '0';
				ctrl_CNT_MOEDA2 <= '0';
				ctrl_RMV_MOEDA <= '0';
				ctrl_RMV_OBST <= '0';
				ctrl_SET_PLAYER <= '0';
				ctrl_CLR_MOEDA <= '0';
				ctrl_CLR_PLAYER <= '0';
				ctrl_CLR_TIMER <= '0';
				ctrl_CLR_START <= '0';
				ctrl_RENDER <= '1';
				ctrl_CMD <= "100";
				
				if ctrl_START = '1' then
					prox_estado <= s2;
				else 
					prox_estado <= s1;
				end if;
			
			when s2 => --CLEAR EM TODOS OS REGISTRADORES
				ctrl_LFSR_SHFT <= '0';
				ctrl_CNT_MOEDA1 <= '0';
				ctrl_CNT_MOEDA2 <= '0';
				ctrl_RMV_MOEDA <= '0';
				ctrl_RMV_OBST <= '0';
				ctrl_SET_PLAYER <= '0';
				ctrl_CLR_MOEDA <= '1';
				ctrl_CLR_PLAYER <= '1';
				ctrl_CLR_TIMER <= '1';
				ctrl_CLR_START <= '1';
				ctrl_RENDER <= '0';
				ctrl_CMD <= "000";
			
				prox_estado <= s3;
				
			when s3 => --TESTA SE HA UMA MOEDA  NA POSICAO DO PLAYER
				ctrl_LFSR_SHFT <= '0';
				ctrl_CNT_MOEDA1 <= '0';
				ctrl_CNT_MOEDA2 <= '0';
				ctrl_RMV_MOEDA <= '0';
				ctrl_RMV_OBST <= '0';
				ctrl_SET_PLAYER <= '0';
				ctrl_CLR_MOEDA <= '0';
				ctrl_CLR_PLAYER <= '0';
				ctrl_CLR_TIMER <= '0';
				ctrl_CLR_START <= '0';
				ctrl_RENDER <= '0';
				ctrl_CMD <= "000";
				
				if ctrl_Q0_MOEDA = '1' then
					prox_estado <= s4;
				else 
					prox_estado <= s8;
				end if;
			
			when s4 => --TESTA SE O PLAYER COLIDIU COM UMA MOEDA
				ctrl_LFSR_SHFT <= '0';
				ctrl_CNT_MOEDA1 <= '0';
				ctrl_CNT_MOEDA2 <= '0';
				ctrl_RMV_MOEDA <= '0';
				ctrl_RMV_OBST <= '0';
				ctrl_SET_PLAYER <= '0';
				ctrl_CLR_MOEDA <= '0';
				ctrl_CLR_PLAYER <= '0';
				ctrl_CLR_TIMER <= '0';
				ctrl_CLR_START <= '0';
				ctrl_RENDER <= '0';
				ctrl_CMD <= "000";
				
				if ctrl_COLLECTED = '1' then
					prox_estado <= s5;
				else 
					prox_estado <= s8;
				end if;
			
			when s5 => --TESTA QUAL PLAYER ESTA JOGANDO ATUALMENTE
				ctrl_LFSR_SHFT <= '0';
				ctrl_CNT_MOEDA1 <= '0';
				ctrl_CNT_MOEDA2 <= '0';
				ctrl_RMV_MOEDA <= '0';
				ctrl_RMV_OBST <= '0';
				ctrl_SET_PLAYER <= '0';
				ctrl_CLR_MOEDA <= '0';
				ctrl_CLR_PLAYER <= '0';
				ctrl_CLR_TIMER <= '0';
				ctrl_CLR_START <= '0';
				ctrl_RENDER <= '0';
				ctrl_CMD <= "000";
				
				if ctrl_PLAYER = '1' then
					prox_estado <= s7;
				else 
					prox_estado <= s6;
				end if;
			
			when s6 => --ADICIONA UMA MOEDA AO PLACAR DO PLAYER 1
				ctrl_LFSR_SHFT <= '0';
				ctrl_CNT_MOEDA1 <= '1';
				ctrl_CNT_MOEDA2 <= '0';
				ctrl_RMV_MOEDA <= '0';
				ctrl_RMV_OBST <= '0';
				ctrl_SET_PLAYER <= '0';
				ctrl_CLR_MOEDA <= '0';
				ctrl_CLR_PLAYER <= '0';
				ctrl_CLR_TIMER <= '0';
				ctrl_CLR_START <= '0';
				ctrl_RENDER <= '0';
				ctrl_CMD <= "000";
			
				prox_estado <= sa8;
			
			when s7 => --ADICIONA UMA MOEDA AO PLACAR DO PLAYER 2
				ctrl_LFSR_SHFT <= '0';
				ctrl_CNT_MOEDA1 <= '0';
				ctrl_CNT_MOEDA2 <= '1';
				ctrl_RMV_MOEDA <= '0';
				ctrl_RMV_OBST <= '0';
				ctrl_SET_PLAYER <= '0';
				ctrl_CLR_MOEDA <= '0';
				ctrl_CLR_PLAYER <= '0';
				ctrl_CLR_TIMER <= '0';
				ctrl_CLR_START <= '0';
				ctrl_RENDER <= '0';
				ctrl_CMD <= "000";
			
				prox_estado <= sa8;
			

				when sa8 => --EXCLUI A MOEDA DO REGISTRADOR 
				ctrl_LFSR_SHFT <= '0';
				ctrl_CNT_MOEDA1 <= '0';
				ctrl_CNT_MOEDA2 <= '0';
				ctrl_RMV_MOEDA <= '1';
				ctrl_RMV_OBST <= '0';
				ctrl_SET_PLAYER <= '0';
				ctrl_CLR_MOEDA <= '0';
				ctrl_CLR_PLAYER <= '0';
				ctrl_CLR_TIMER <= '0';
				ctrl_CLR_START <= '0';
				ctrl_RENDER <= '0';
				ctrl_CMD <= "000";

				prox_estado <= s8;


			when s8 => --TESTA SE TEM UM OBSTACULO NA POS DO PLAYER 
				ctrl_LFSR_SHFT <= '0';
				ctrl_CNT_MOEDA1 <= '0';
				ctrl_CNT_MOEDA2 <= '0';
				ctrl_RMV_MOEDA <= '0';
				ctrl_RMV_OBST <= '0';
				ctrl_SET_PLAYER <= '0';
				ctrl_CLR_MOEDA <= '0';
				ctrl_CLR_PLAYER <= '0';
				ctrl_CLR_TIMER <= '0';
				ctrl_CLR_START <= '0';
				ctrl_RENDER <= '0';
				ctrl_CMD <= "000";
				
				if ctrl_Q0_OBST = '1' then
					prox_estado <= s9;
				else 
					prox_estado <= s19;
				end if;
			
			when s9 => -- TESTA SE O PLAYER COLIDIU COM UM OBSTACULO
				ctrl_LFSR_SHFT <= '0';
				ctrl_CNT_MOEDA1 <= '0';
				ctrl_CNT_MOEDA2 <= '0';
				ctrl_RMV_MOEDA <= '0';
				ctrl_RMV_OBST <= '0';
				ctrl_SET_PLAYER <= '0';
				ctrl_CLR_MOEDA <= '0';
				ctrl_CLR_PLAYER <= '0';
				ctrl_CLR_TIMER <= '0';
				ctrl_CLR_START <= '0';
				ctrl_RENDER <= '0';
				ctrl_CMD <= "000";
				
				if ctrl_ENDED = '1' then
					prox_estado <= s13;
				else 
					prox_estado <= s10;
				end if;
			
			when s10 => -- TESTA SE O RENDER JA FOI CONCLUIDO
				ctrl_LFSR_SHFT <= '0';
				ctrl_CNT_MOEDA1 <= '0';
				ctrl_CNT_MOEDA2 <= '0';
				ctrl_RMV_MOEDA <= '0';
				ctrl_RMV_OBST <= '0';
				ctrl_SET_PLAYER <= '0';
				ctrl_CLR_MOEDA <= '0';
				ctrl_CLR_PLAYER <= '0';
				ctrl_CLR_TIMER <= '0';
				ctrl_CLR_START <= '0';
				ctrl_RENDER <= '0';
				ctrl_CMD <= "000";
				
				if ctrl_FINISH = '1' then
					prox_estado <= s11;
				else 
					prox_estado <= s10;
				end if;
			
			when s11 => --TIMER ++
				ctrl_LFSR_SHFT <= '0';
				ctrl_CNT_MOEDA1 <= '0';
				ctrl_CNT_MOEDA2 <= '0';
				ctrl_RMV_MOEDA <= '0';
				ctrl_RMV_OBST <= '0';
				ctrl_SET_PLAYER <= '0';
				ctrl_CLR_MOEDA <= '0';
				ctrl_CLR_PLAYER <= '0';
				ctrl_CLR_TIMER <= '0';
				ctrl_CLR_START <= '0';
				ctrl_RENDER <= '0';
				ctrl_CMD <= "000";
				
				if ctrl_FRAME_TIMER = '1' then
					prox_estado <= s12;
				else 
					prox_estado <= s11;
				end if;
			
			when s12 => --LFSR SHIFT / CLEAR TIMER
				ctrl_LFSR_SHFT <= '1';
				ctrl_CNT_MOEDA1 <= '0';
				ctrl_CNT_MOEDA2 <= '0';
				ctrl_RMV_MOEDA <= '0';
				ctrl_RMV_OBST <= '0';
				ctrl_SET_PLAYER <= '0';
				ctrl_CLR_MOEDA <= '0';
				ctrl_CLR_PLAYER <= '0';
				ctrl_CLR_TIMER <= '1';
				ctrl_CLR_START <= '0';
				ctrl_RENDER <= '0';
				ctrl_CMD <= "000";
		
				prox_estado <= s3;
			
			when s13 => --EXCLUI O OBSTACULO DO REGISTRADOR/ TESTA SE O PLAYER 1 OU 2 ESTA JOGANDO
				ctrl_LFSR_SHFT <= '0';
				ctrl_CNT_MOEDA1 <= '0';
				ctrl_CNT_MOEDA2 <= '0';
				ctrl_RMV_MOEDA <= '0';
				ctrl_RMV_OBST <= '1';
				ctrl_SET_PLAYER <= '0';
				ctrl_CLR_MOEDA <= '0';
				ctrl_CLR_PLAYER <= '0';
				ctrl_CLR_TIMER <= '0';
				ctrl_CLR_START <= '0';
				ctrl_RENDER <= '0';
				ctrl_CMD <= "000";
				
				if ctrl_PLAYER = '1' then
					prox_estado <= s16;
				else 
					prox_estado <= s14;
				end if;
			
			when s14 => --TROCA O PLAYER 1 PARA PLAYER 2 / CLEAR NO REGISTRADOR DE START
				ctrl_LFSR_SHFT <= '0';
				ctrl_CNT_MOEDA1 <= '0';
				ctrl_CNT_MOEDA2 <= '0';
				ctrl_RMV_MOEDA <= '0';
				ctrl_RMV_OBST <= '0';
				ctrl_SET_PLAYER <= '1';
				ctrl_CLR_MOEDA <= '0';
				ctrl_CLR_PLAYER <= '0';
				ctrl_CLR_TIMER <= '0';
				ctrl_CLR_START <= '1';
				ctrl_RENDER <= '0';
				ctrl_CMD <= "000";
		
				prox_estado <= s15;
				
			when s15 => --ESCREVE NO LCD " P2 " ATE APERTAR START
				ctrl_LFSR_SHFT <= '0';
				ctrl_CNT_MOEDA1 <= '0';
				ctrl_CNT_MOEDA2 <= '0';
				ctrl_RMV_MOEDA <= '0';
				ctrl_RMV_OBST <= '0';
				ctrl_SET_PLAYER <= '0';
				ctrl_CLR_MOEDA <= '0';
				ctrl_CLR_PLAYER <= '0';
				ctrl_CLR_TIMER <= '0';
				ctrl_CLR_START <= '0';
				ctrl_RENDER <= '1';
				ctrl_CMD <= "101";
				
				if ctrl_START = '1' then
					prox_estado <= s3;
				else 
					prox_estado <= s15;
				end if;
			
			when s16 => --DECIDE QUAL O RESULTADO DA PARTIDA
				ctrl_LFSR_SHFT <= '0';
				ctrl_CNT_MOEDA1 <= '0';
				ctrl_CNT_MOEDA2 <= '0';
				ctrl_RMV_MOEDA <= '0';
				ctrl_RMV_OBST <= '0';
				ctrl_SET_PLAYER <= '0';
				ctrl_CLR_MOEDA <= '0';
				ctrl_CLR_PLAYER <= '0';
				ctrl_CLR_TIMER <= '0';
				ctrl_CLR_START <= '0';
				ctrl_RENDER <= '0';
				ctrl_CMD <= "000";
				
				if ctrl_RESULT = "010" then
					prox_estado <= s18;
				elsif ctrl_RESULT = "001"  then
					prox_estado <= s19;
				else 
					prox_estado <= s17;
				end if;
			
			when s17 => --EMPATE
				ctrl_LFSR_SHFT <= '0';
				ctrl_CNT_MOEDA1 <= '0';
				ctrl_CNT_MOEDA2 <= '0';
				ctrl_RMV_MOEDA <= '0';
				ctrl_RMV_OBST <= '0';
				ctrl_SET_PLAYER <= '0';
				ctrl_CLR_MOEDA <= '0';
				ctrl_CLR_PLAYER <= '0';
				ctrl_CLR_TIMER <= '0';
				ctrl_CLR_START <= '0';
				ctrl_RENDER <= '1';
				ctrl_CMD <= "011";
				
				if ctrl_START = '1' then
					prox_estado <= s2;
				else 
					prox_estado <= s17;
				end if;
					
			when s18 => --PLAYER 1 GANHOU
				ctrl_LFSR_SHFT <= '0';
				ctrl_CNT_MOEDA1 <= '0';
				ctrl_CNT_MOEDA2 <= '0';
				ctrl_RMV_MOEDA <= '0';
				ctrl_RMV_OBST <= '0';
				ctrl_SET_PLAYER <= '0';
				ctrl_CLR_MOEDA <= '0';
				ctrl_CLR_PLAYER <= '0';
				ctrl_CLR_TIMER <= '0';
				ctrl_CLR_START <= '0';
				ctrl_RENDER <= '1';
				ctrl_CMD <= "110";
				
				if ctrl_START = '1' then
					prox_estado <= s2;
				else 
					prox_estado <= s18;
				end if;
					
			when s19 => --PLAYER 2 GANHOU
				ctrl_LFSR_SHFT <= '0';
				ctrl_CNT_MOEDA1 <= '0';
				ctrl_CNT_MOEDA2 <= '0';
				ctrl_RMV_MOEDA <= '0';
				ctrl_RMV_OBST <= '0';
				ctrl_SET_PLAYER <= '0';
				ctrl_CLR_MOEDA <= '0';
				ctrl_CLR_PLAYER <= '0';
				ctrl_CLR_TIMER <= '0';
				ctrl_CLR_START <= '0';
				ctrl_RENDER <= '1';
				ctrl_CMD <= "111";
				
				if ctrl_START = '1' then
					prox_estado <= s2;
				else 
					prox_estado <= s19;
				end if;
			
			when others => 
				ctrl_LFSR_SHFT <= '0';
				ctrl_CNT_MOEDA1 <= '0';
				ctrl_CNT_MOEDA2 <= '0';
				ctrl_RMV_MOEDA <= '0';
				ctrl_RMV_OBST <= '0';
				ctrl_SET_PLAYER <= '0';
				ctrl_CLR_MOEDA <= '0';
				ctrl_CLR_PLAYER <= '0';
				ctrl_CLR_TIMER <= '0';
				ctrl_CLR_START <= '0';
				ctrl_RENDER <= '0';
				ctrl_CMD <= "000";
				
				prox_estado <= s0;
			
		end case;
	end process;
	
end arch;

GAME/tb_controladora_jogo.vhd
library ieee;
use ieee.std_logic_1164.all;
use ieee.numeric_std.all;

entity tb_controladora_jogo is
end entity tb_controladora_jogo;

architecture tb of tb_controladora_jogo is
    
    component controladora_jogo is
        port(
            --entradas
            ctrl_CLK : in std_logic;
            ctrl_FINISH : in std_logic;
            ctrl_START : in std_logic;
            ctrl_Q0_MOEDA : in std_logic;
            ctrl_COLLECTED : in std_logic;
            ctrl_Q0_OBST : in std_logic;
            ctrl_ENDED : in std_logic;
            ctrl_PLAYER : in std_logic;
            ctrl_FRAME_TIMER : in std_logic;
            ctrl_RESULT : in std_logic_vector(2 downto 0);
            
            --saidas
            ctrl_LFSR_SHFT : out std_logic;
            ctrl_CNT_MOEDA1: out std_logic;
            ctrl_CNT_MOEDA2 : out std_logic;
            ctrl_RMV_MOEDA : out std_logic;
            ctrl_RMV_OBST : out std_logic;
            ctrl_SET_PLAYER : out std_logic;
            ctrl_CLR_MOEDA : out std_logic;
            ctrl_CLR_PLAYER : out std_logic;
            ctrl_CLR_TIMER : out std_logic;
            ctrl_CLR_START : out std_logic;
            ctrl_RENDER : out std_logic;
            ctrl_CMD : out std_logic_vector(2 downto 0)
            );
    end component;

    signal s_clk, s_finish, s_start, s_q0_moeda, s_collected, s_q0_obst, s_ended, s_player, s_frame_timer : std_logic := '0';
    signal s_lfsr_shift, s_cnt_moeda1, s_cnt_moeda2, s_rmv_moeda, s_rmv_obst,s_set_player, s_clr_moeda,s_clr_player, s_clr_timer, s_clr_start, s_render : std_logic;
    signal s_result, s_cmd : std_logic_vector(2 downto 0);


begin
    
    controladora : controladora_jogo port map(
        --entradas
        ctrl_CLK => s_clk,
        ctrl_FINISH => s_finish,
        ctrl_START => s_start,
        ctrl_Q0_MOEDA => s_q0_moeda,
        ctrl_COLLECTED => s_collected,
        ctrl_Q0_OBST => s_q0_obst,
        ctrl_ENDED => s_ended,
        ctrl_PLAYER => s_player,
        ctrl_FRAME_TIMER => s_frame_timer,
        ctrl_RESULT => s_result,
        
        --saidas
        ctrl_LFSR_SHFT => s_lfsr_shift,
        ctrl_CNT_MOEDA1 => s_cnt_moeda1,
        ctrl_CNT_MOEDA2 => s_cnt_moeda2,
        ctrl_RMV_MOEDA => s_rmv_moeda,
        ctrl_RMV_OBST => s_rmv_obst,
        ctrl_SET_PLAYER => s_set_player,
        ctrl_CLR_MOEDA => s_clr_moeda,
        ctrl_CLR_PLAYER => s_clr_player,
        ctrl_CLR_TIMER => s_clr_timer,
        ctrl_CLR_START => s_clr_start,
        ctrl_RENDER => s_render,
        ctrl_CMD => s_cmd
        );

    s_clk <= not s_clk after 10 ns;
    
    s_finish <= '1';

    s_start <= '1';

    s_q0_moeda <= '0';

    s_collected <= '1';

    s_q0_obst <= '1';

    s_ended <= '1';

    s_player <= '0', '1' after 143 ns;

    s_frame_timer <= '0';

    s_result <= "100";

    
end architecture tb;

GAME/test_controladora.vcd
$date
  Sat Dec 17 23:37:18 2022
$end
$version
  GHDL v0
$end
$timescale
  1 fs
$end
$scope module standard $end
$upscope $end
$scope module std_logic_1164 $end
$upscope $end
$scope module numeric_std $end
$upscope $end
$scope module tb_controladora_jogo $end
$var reg 1 ! s_clk $end
$var reg 1 " s_finish $end
$var reg 1 # s_start $end
$var reg 1 $ s_q0_moeda $end
$var reg 1 % s_collected $end
$var reg 1 & s_q0_obst $end
$var reg 1 ' s_ended $end
$var reg 1 ( s_player $end
$var reg 1 ) s_frame_timer $end
$var reg 1 * s_lfsr_shift $end
$var reg 1 + s_cnt_moeda1 $end
$var reg 1 , s_cnt_moeda2 $end
$var reg 1 - s_rmv_moeda $end
$var reg 1 . s_rmv_obst $end
$var reg 1 / s_set_player $end
$var reg 1 0 s_clr_moeda $end
$var reg 1 1 s_clr_player $end
$var reg 1 2 s_clr_timer $end
$var reg 1 3 s_clr_start $end
$var reg 1 4 s_render $end
$var reg 3 5 s_result[2:0] $end
$var reg 3 6 s_cmd[2:0] $end
$scope module controladora $end
$var reg 1 7 ctrl_clk $end
$var reg 1 8 ctrl_finish $end
$var reg 1 9 ctrl_start $end
$var reg 1 : ctrl_q0_moeda $end
$var reg 1 ; ctrl_collected $end
$var reg 1 < ctrl_q0_obst $end
$var reg 1 = ctrl_ended $end
$var reg 1 > ctrl_player $end
$var reg 1 ? ctrl_frame_timer $end
$var reg 3 @ ctrl_result[2:0] $end
$var reg 1 A ctrl_lfsr_shft $end
$var reg 1 B ctrl_cnt_moeda1 $end
$var reg 1 C ctrl_cnt_moeda2 $end
$var reg 1 D ctrl_rmv_moeda $end
$var reg 1 E ctrl_rmv_obst $end
$var reg 1 F ctrl_set_player $end
$var reg 1 G ctrl_clr_moeda $end
$var reg 1 H ctrl_clr_player $end
$var reg 1 I ctrl_clr_timer $end
$var reg 1 J ctrl_clr_start $end
$var reg 1 K ctrl_render $end
$var reg 3 L ctrl_cmd[2:0] $end
$comment estado_atual is not handled $end
$comment prox_estado is not handled $end
$upscope $end
$upscope $end
$enddefinitions $end
#0
0!
1"
1#
0$
1%
1&
1'
0(
0)
0*
0+
0,
0-
0.
0/
00
01
02
03
04
b100 5
b000 6
07
18
19
0:
1;
1<
1=
0>
0?
b100 @
0A
0B
0C
0D
0E
0F
0G
0H
0I
0J
0K
b000 L
#10000000
1!
14
b100 6
17
1K
b100 L
#20000000
0!
07
#30000000
1!
10
11
12
13
04
b000 6
17
1G
1H
1I
1J
0K
b000 L
#40000000
0!
07
#50000000
1!
00
01
02
03
17
0G
0H
0I
0J
#60000000
0!
07
#70000000
1!
1-
17
1D
#80000000
0!
07
#90000000
1!
0-
17
0D
#100000000
0!
07
#110000000
1!
1/
13
17
1F
1J
#120000000
0!
07
#130000000
1!
0/
03
14
b101 6
17
0F
0J
1K
b101 L
#140000000
0!
07
#150000000
1!
04
b000 6
17
0K
b000 L
#160000000
0!
07
#170000000
1!
17
#180000000
0!
07
#190000000
1!
1+
17
1B
#200000000
0!
07
#210000000
1!
0+
1-
17
0B
1D
#220000000
0!
07
#230000000
1!
0-
17
0D
#240000000
0!
07
#250000000
1!
1/
13
17
1F
1J
#260000000
0!
07
#270000000
1!
0/
03
14
b101 6
17
0F
0J
1K
b101 L
#280000000
0!
07
#290000000
1!
04
b000 6
17
0K
b000 L
#300000000
0!
07
#310000000
1!
17
#320000000
0!
07
#330000000
1!
1+
17
1B
#340000000
0!
07
#350000000
1!
0+
1-
17
0B
1D
#360000000
0!
07
#370000000
1!
0-
17
0D
#380000000
0!
07
#390000000
1!
1/
13
17
1F
1J
#400000000
0!
07
#410000000
1!
0/
03
14
b101 6
17
0F
0J
1K
b101 L
#420000000
0!
07
#430000000
1!
04
b000 6
17
0K
b000 L
#440000000
0!
07
#450000000
1!
17
#460000000
0!
07
#470000000
1!
1+
17
1B
#480000000
0!
07
#490000000
1!
0+
1-
17
0B
1D
#500000000
0!
07
#510000000
1!
0-
17
0D
#520000000
0!
07
#530000000
1!
1/
13
17
1F
1J
#540000000
0!
07
#550000000
1!
0/
03
14
b101 6
17
0F
0J
1K
b101 L
#560000000
0!
07
#570000000
1!
04
b000 6
17
0K
b000 L
