LCD/comp_10/comp_10.vhd
library ieee;
use ieee.std_logic_1164.all;
use ieee.numeric_std.all;

entity comp_10 is
	port(
			comp_A : in std_logic_vector(9 downto 0);
			comp_B : in std_logic_vector(9 downto 0);
			comp_S : out std_logic
		);
end comp_10;

architecture arch of comp_10 is
begin
	comp_S <= '0' when comp_A < comp_B else '1'; 
end arch;

LCD/test/cont_10.vhd
library ieee;
use ieee.std_logic_1164.all;
use ieee.numeric_std.all;

entity cont_10 is
	port(
			cnt10_clk : in std_logic;
			cnt10_reset : in std_logic;
			cnt10_h : in std_logic;
			cnt10_q : out std_logic_vector(9 downto 0)
		);
end cont_10;

architecture arch of cont_10 is
begin
	process(cnt10_clk,cnt10_reset)
		variable i : unsigned(9 downto 0) := "0000000000"; 
		begin
		
		if cnt10_reset = '1' then
			i := "0000000000";
		else
			if rising_edge(cnt10_clk) and cnt10_h = '1' then
				i := i + "0000000001";
			end if;
		end if;
		
		cnt10_q <= std_logic_vector(i);
	end process;
end arch;

LCD/test/tb_cont_10.vhd
library ieee;
use ieee.std_logic_1164.all;
use ieee.numeric_std.all;

entity tb_cont_10 is
end tb_cont_10;

architecture arch of tb_cont_10 is
    component cont_10 is
        port(
                cnt10_clk : in std_logic;
                cnt10_reset : in std_logic;
                cnt10_h : in std_logic;
                cnt10_q : out std_logic_vector(9 downto 0)
            );
    end component;

    component comp_10 is
        port(
                comp_A : in std_logic_vector(9 downto 0);
                comp_B : in std_logic_vector(9 downto 0);
                comp_S : out std_logic
            );
    end component;

    signal clk,reset,h : std_logic := '0';
    signal S : std_logic;
    signal q, A, B: std_logic_vector(9 downto 0) ;

begin

    tb : cont_10 port map(
        cnt10_clk => clk,
        cnt10_reset => reset,
        cnt10_h => h,
        cnt10_q => q
    );

    cmp : comp_10 port map(
        comp_A => A,
        comp_B => B,
        comp_S => S
    );

    clk <= not clk after 1 ns;
    h <= '1';
    reset <= '0';

    A <= q;

    B <= "1111101000";
end arch ; -- arch

LCD/test/test.vcd
$date
  Sat Dec 17 19:24:08 2022
$end
$version
  GHDL v0
$end
$timescale
  1 fs
$end
$scope module standard $end
$upscope $end
$scope module std_logic_1164 $end
$upscope $end
$scope module numeric_std $end
$upscope $end
$scope module tb_cont_10 $end
$var reg 1 ! clk $end
$var reg 1 " reset $end
$var reg 1 # h $end
$var reg 1 $ s $end
$var reg 10 % q[9:0] $end
$var reg 10 & a[9:0] $end
$var reg 10 ' b[9:0] $end
$scope module tb $end
$var reg 1 ( cnt10_clk $end
$var reg 1 ) cnt10_reset $end
$var reg 1 * cnt10_h $end
$var reg 10 + cnt10_q[9:0] $end
$upscope $end
$scope module cmp $end
$var reg 10 , comp_a[9:0] $end
$var reg 10 - comp_b[9:0] $end
$var reg 1 . comp_s $end
$upscope $end
$upscope $end
$enddefinitions $end
#0
0!
0"
1#
0$
b0000000000 %
b0000000000 &
b1111101000 '
0(
0)
1*
b0000000000 +
b0000000000 ,
b1111101000 -
0.
#1000000
1!
b0000000001 %
b0000000001 &
1(
b0000000001 +
b0000000001 ,
#2000000
0!
0(
#3000000
1!
b0000000010 %
b0000000010 &
1(
b0000000010 +
b0000000010 ,
#4000000
0!
0(
#5000000
1!
b0000000011 %
b0000000011 &
1(
b0000000011 +
b0000000011 ,
#6000000
0!
0(
#7000000
1!
b0000000100 %
b0000000100 &
1(
b0000000100 +
b0000000100 ,
#8000000
0!
0(
#9000000
1!
b0000000101 %
b0000000101 &
1(
b0000000101 +
b0000000101 ,
#10000000
0!
0(
#11000000
1!
b0000000110 %
b0000000110 &
1(
b0000000110 +
b0000000110 ,
#12000000
0!
0(
#13000000
1!
b0000000111 %
b0000000111 &
1(
b0000000111 +
b0000000111 ,
#14000000
0!
0(
#15000000
1!
b0000001000 %
b0000001000 &
1(
b0000001000 +
b0000001000 ,
#16000000
0!
0(
#17000000
1!
b0000001001 %
b0000001001 &
1(
b0000001001 +
b0000001001 ,
#18000000
0!
0(
#19000000
1!
b0000001010 %
b0000001010 &
1(
b0000001010 +
b0000001010 ,
#20000000
0!
0(
#21000000
1!
b0000001011 %
b0000001011 &
1(
b0000001011 +
b0000001011 ,
#22000000
0!
0(
#23000000
1!
b0000001100 %
b0000001100 &
1(
b0000001100 +
b0000001100 ,
#24000000
0!
0(
#25000000
1!
b0000001101 %
b0000001101 &
1(
b0000001101 +
b0000001101 ,
#26000000
0!
0(
#27000000
1!
b0000001110 %
b0000001110 &
1(
b0000001110 +
b0000001110 ,
#28000000
0!
0(
#29000000
1!
b0000001111 %
b0000001111 &
1(
b0000001111 +
b0000001111 ,
#30000000
0!
0(
#31000000
1!
b0000010000 %
b0000010000 &
1(
b0000010000 +
b0000010000 ,
#32000000
0!
0(
#33000000
1!
b0000010001 %
b0000010001 &
1(
b0000010001 +
b0000010001 ,
#34000000
0!
0(
#35000000
1!
b0000010010 %
b0000010010 &
1(
b0000010010 +
b0000010010 ,
#36000000
0!
0(
#37000000
1!
b0000010011 %
b0000010011 &
1(
b0000010011 +
b0000010011 ,
#38000000
0!
0(
#39000000
1!
b0000010100 %
b0000010100 &
1(
b0000010100 +
b0000010100 ,
#40000000
0!
0(
#41000000
1!
b0000010101 %
b0000010101 &
1(
b0000010101 +
b0000010101 ,
#42000000
0!
0(
#43000000
1!
b0000010110 %
b0000010110 &
1(
b0000010110 +
b0000010110 ,
#44000000
0!
0(
#45000000
1!
b0000010111 %
b0000010111 &
1(
b0000010111 +
b0000010111 ,
#46000000
0!
0(
#47000000
1!
b0000011000 %
b0000011000 &
1(
b0000011000 +
b0000011000 ,
#48000000
0!
0(
#49000000
1!
b0000011001 %
b0000011001 &
1(
b0000011001 +
b0000011001 ,
#50000000
0!
0(
#51000000
1!
b0000011010 %
b0000011010 &
1(
b0000011010 +
b0000011010 ,
#52000000
0!
0(
#53000000
1!
b0000011011 %
b0000011011 &
1(
b0000011011 +
b0000011011 ,
#54000000
0!
0(
#55000000
1!
b0000011100 %
b0000011100 &
1(
b0000011100 +
b0000011100 ,
#56000000
0!
0(
#57000000
1!
b0000011101 %
b0000011101 &
1(
b0000011101 +
b0000011101 ,
#58000000
0!
0(
#59000000
1!
b0000011110 %
b0000011110 &
1(
b0000011110 +
b0000011110 ,
#60000000
0!
0(
#61000000
1!
b0000011111 %
b0000011111 &
1(
b0000011111 +
b0000011111 ,
#62000000
0!
0(
#63000000
1!
b0000100000 %
b0000100000 &
1(
b0000100000 +
b0000100000 ,
#64000000
0!
0(
#65000000
1!
b0000100001 %
b0000100001 &
1(
b0000100001 +
b0000100001 ,
#66000000
0!
0(
#67000000
1!
b0000100010 %
b0000100010 &
1(
b0000100010 +
b0000100010 ,
#68000000
0!
0(
#69000000
1!
b0000100011 %
b0000100011 &
1(
b0000100011 +
b0000100011 ,
#70000000
0!
0(
#71000000
1!
b0000100100 %
b0000100100 &
1(
b0000100100 +
b0000100100 ,
#72000000
0!
0(
#73000000
1!
b0000100101 %
b0000100101 &
1(
b0000100101 +
b0000100101 ,
#74000000
0!
0(
#75000000
1!
b0000100110 %
b0000100110 &
1(
b0000100110 +
b0000100110 ,
#76000000
0!
0(
#77000000
1!
b0000100111 %
b0000100111 &
1(
b0000100111 +
b0000100111 ,
#78000000
0!
0(
#79000000
1!
b0000101000 %
b0000101000 &
1(
b0000101000 +
b0000101000 ,
#80000000
0!
0(
#81000000
1!
b0000101001 %
b0000101001 &
1(
b0000101001 +
b0000101001 ,
#82000000
0!
0(
#83000000
1!
b0000101010 %
b0000101010 &
1(
b0000101010 +
b0000101010 ,
#84000000
0!
0(
#85000000
1!
b0000101011 %
b0000101011 &
1(
b0000101011 +
b0000101011 ,
#86000000
0!
0(
#87000000
1!
b0000101100 %
b0000101100 &
1(
b0000101100 +
b0000101100 ,
#88000000
0!
0(
#89000000
1!
b0000101101 %
b0000101101 &
1(
b0000101101 +
b0000101101 ,
#90000000
0!
0(
#91000000
1!
b0000101110 %
b0000101110 &
1(
b0000101110 +
b0000101110 ,
#92000000
0!
0(
#93000000
1!
b0000101111 %
b0000101111 &
1(
b0000101111 +
b0000101111 ,
#94000000
0!
0(
#95000000
1!
b0000110000 %
b0000110000 &
1(
b0000110000 +
b0000110000 ,
#96000000
0!
0(
#97000000
1!
b0000110001 %
b0000110001 &
1(
b0000110001 +
b0000110001 ,
#98000000
0!
0(
#99000000
1!
b0000110010 %
b0000110010 &
1(
b0000110010 +
b0000110010 ,
#100000000
0!
0(
#101000000
1!
b0000110011 %
b0000110011 &
1(
b0000110011 +
b0000110011 ,
#102000000
0!
0(
#103000000
1!
b0000110100 %
b0000110100 &
1(
b0000110100 +
b0000110100 ,
#104000000
0!
0(
#105000000
1!
b0000110101 %
b0000110101 &
1(
b0000110101 +
b0000110101 ,
#106000000
0!
0(
#107000000
1!
b0000110110 %
b0000110110 &
1(
b0000110110 +
b0000110110 ,
#108000000
0!
0(
#109000000
1!
b0000110111 %
b0000110111 &
1(
b0000110111 +
b0000110111 ,
#110000000
0!
0(
#111000000
1!
b0000111000 %
b0000111000 &
1(
b0000111000 +
b0000111000 ,
#112000000
0!
0(
#113000000
1!
b0000111001 %
b0000111001 &
1(
b0000111001 +
b0000111001 ,
#114000000
0!
0(
#115000000
1!
b0000111010 %
b0000111010 &
1(
b0000111010 +
b0000111010 ,
#116000000
0!
0(
#117000000
1!
b0000111011 %
b0000111011 &
1(
b0000111011 +
b0000111011 ,
#118000000
0!
0(
#119000000
1!
b0000111100 %
b0000111100 &
1(
b0000111100 +
b0000111100 ,
#120000000
0!
0(
#121000000
1!
b0000111101 %
b0000111101 &
1(
b0000111101 +
b0000111101 ,
#122000000
0!
0(
#123000000
1!
b0000111110 %
b0000111110 &
1(
b0000111110 +
b0000111110 ,
#124000000
0!
0(
#125000000
1!
b0000111111 %
b0000111111 &
1(
b0000111111 +
b0000111111 ,
#126000000
0!
0(
#127000000
1!
b0001000000 %
b0001000000 &
1(
b0001000000 +
b0001000000 ,
#128000000
0!
0(
#129000000
1!
b0001000001 %
b0001000001 &
1(
b0001000001 +
b0001000001 ,
#130000000
0!
0(
#131000000
1!
b0001000010 %
b0001000010 &
1(
b0001000010 +
b0001000010 ,
#132000000
0!
0(
#133000000
1!
b0001000011 %
b0001000011 &
1(
b0001000011 +
b0001000011 ,
#134000000
0!
0(
#135000000
1!
b0001000100 %
b0001000100 &
1(
b0001000100 +
b0001000100 ,
#136000000
0!
0(
#137000000
1!
b0001000101 %
b0001000101 &
1(
b0001000101 +
b0001000101 ,
#138000000
0!
0(
#139000000
1!
b0001000110 %
b0001000110 &
1(
b0001000110 +
b0001000110 ,
#140000000
0!
0(
#141000000
1!
b0001000111 %
b0001000111 &
1(
b0001000111 +
b0001000111 ,
#142000000
0!
0(
#143000000
1!
b0001001000 %
b0001001000 &
1(
b0001001000 +
b0001001000 ,
#144000000
0!
0(
#145000000
1!
b0001001001 %
b0001001001 &
1(
b0001001001 +
b0001001001 ,
#146000000
0!
0(
#147000000
1!
b0001001010 %
b0001001010 &
1(
b0001001010 +
b0001001010 ,
#148000000
0!
0(
#149000000
1!
b0001001011 %
b0001001011 &
1(
b0001001011 +
b0001001011 ,
#150000000
0!
0(
#151000000
1!
b0001001100 %
b0001001100 &
1(
b0001001100 +
b0001001100 ,
#152000000
0!
0(
#153000000
1!
b0001001101 %
b0001001101 &
1(
b0001001101 +
b0001001101 ,
#154000000
0!
0(
#155000000
1!
b0001001110 %
b0001001110 &
1(
b0001001110 +
b0001001110 ,
#156000000
0!
0(
#157000000
1!
b0001001111 %
b0001001111 &
1(
b0001001111 +
b0001001111 ,
#158000000
0!
0(
#159000000
1!
b0001010000 %
b0001010000 &
1(
b0001010000 +
b0001010000 ,
#160000000
0!
0(
#161000000
1!
b0001010001 %
b0001010001 &
1(
b0001010001 +
b0001010001 ,
#162000000
0!
0(
#163000000
1!
b0001010010 %
b0001010010 &
1(
b0001010010 +
b0001010010 ,
#164000000
0!
0(
#165000000
1!
b0001010011 %
b0001010011 &
1(
b0001010011 +
b0001010011 ,
#166000000
0!
0(
#167000000
1!
b0001010100 %
b0001010100 &
1(
b0001010100 +
b0001010100 ,
#168000000
0!
0(
#169000000
1!
b0001010101 %
b0001010101 &
1(
b0001010101 +
b0001010101 ,
#170000000
0!
0(
#171000000
1!
b0001010110 %
b0001010110 &
1(
b0001010110 +
b0001010110 ,
#172000000
0!
0(
#173000000
1!
b0001010111 %
b0001010111 &
1(
b0001010111 +
b0001010111 ,
#174000000
0!
0(
#175000000
1!
b0001011000 %
b0001011000 &
1(
b0001011000 +
b0001011000 ,
#176000000
0!
0(
#177000000
1!
b0001011001 %
b0001011001 &
1(
b0001011001 +
b0001011001 ,
#178000000
0!
0(
#179000000
1!
b0001011010 %
b0001011010 &
1(
b0001011010 +
b0001011010 ,
#180000000
0!
0(
#181000000
1!
b0001011011 %
b0001011011 &
1(
b0001011011 +
b0001011011 ,
#182000000
0!
0(
#183000000
1!
b0001011100 %
b0001011100 &
1(
b0001011100 +
b0001011100 ,
#184000000
0!
0(
#185000000
1!
b0001011101 %
b0001011101 &
1(
b0001011101 +
b0001011101 ,
#186000000
0!
0(
#187000000
1!
b0001011110 %
b0001011110 &
1(
b0001011110 +
b0001011110 ,
#188000000
0!
0(
#189000000
1!
b0001011111 %
b0001011111 &
1(
b0001011111 +
b0001011111 ,
#190000000
0!
0(
#191000000
1!
b0001100000 %
b0001100000 &
1(
b0001100000 +
b0001100000 ,
#192000000
0!
0(
#193000000
1!
b0001100001 %
b0001100001 &
1(
b0001100001 +
b0001100001 ,
#194000000
0!
0(
#195000000
1!
b0001100010 %
b0001100010 &
1(
b0001100010 +
b0001100010 ,
#196000000
0!
0(
#197000000
1!
b0001100011 %
b0001100011 &
1(
b0001100011 +
b0001100011 ,
#198000000
0!
0(
#199000000
1!
b0001100100 %
b0001100100 &
1(
b0001100100 +
b0001100100 ,
#200000000
0!
0(
#201000000
1!
b0001100101 %
b0001100101 &
1(
b0001100101 +
b0001100101 ,
#202000000
0!
0(
#203000000
1!
b0001100110 %
b0001100110 &
1(
b0001100110 +
b0001100110 ,
#204000000
0!
0(
#205000000
1!
b0001100111 %
b0001100111 &
1(
b0001100111 +
b0001100111 ,
#206000000
0!
0(
#207000000
1!
b0001101000 %
b0001101000 &
1(
b0001101000 +
b0001101000 ,
#208000000
0!
0(
#209000000
1!
b0001101001 %
b0001101001 &
1(
b0001101001 +
b0001101001 ,
#210000000
0!
0(
#211000000
1!
b0001101010 %
b0001101010 &
1(
b0001101010 +
b0001101010 ,
#212000000
0!
0(
#213000000
1!
b0001101011 %
b0001101011 &
1(
b0001101011 +
b0001101011 ,
#214000000
0!
0(
#215000000
1!
b0001101100 %
b0001101100 &
1(
b0001101100 +
b0001101100 ,
#216000000
0!
0(
#217000000
1!
b0001101101 %
b0001101101 &
1(
b0001101101 +
b0001101101 ,
#218000000
0!
0(
#219000000
1!
b0001101110 %
b0001101110 &
1(
b0001101110 +
b0001101110 ,
#220000000
0!
0(
#221000000
1!
b0001101111 %
b0001101111 &
1(
b0001101111 +
b0001101111 ,
#222000000
0!
0(
#223000000
1!
b0001110000 %
b0001110000 &
1(
b0001110000 +
b0001110000 ,
#224000000
0!
0(
#225000000
1!
b0001110001 %
b0001110001 &
1(
b0001110001 +
b0001110001 ,
#226000000
0!
0(
#227000000
1!
b0001110010 %
b0001110010 &
1(
b0001110010 +
b0001110010 ,
#228000000
0!
0(
#229000000
1!
b0001110011 %
b0001110011 &
1(
b0001110011 +
b0001110011 ,
#230000000
0!
0(
#231000000
1!
b0001110100 %
b0001110100 &
1(
b0001110100 +
b0001110100 ,
#232000000
0!
0(
#233000000
1!
b0001110101 %
b0001110101 &
1(
b0001110101 +
b0001110101 ,
#234000000
0!
0(
#235000000
1!
b0001110110 %
b0001110110 &
1(
b0001110110 +
b0001110110 ,
#236000000
0!
0(
#237000000
1!
b0001110111 %
b0001110111 &
1(
b0001110111 +
b0001110111 ,
#238000000
0!
0(
#239000000
1!
b0001111000 %
b0001111000 &
1(
b0001111000 +
b0001111000 ,
#240000000
0!
0(
#241000000
1!
b0001111001 %
b0001111001 &
1(
b0001111001 +
b0001111001 ,
#242000000
0!
0(
#243000000
1!
b0001111010 %
b0001111010 &
1(
b0001111010 +
b0001111010 ,
#244000000
0!
0(
#245000000
1!
b0001111011 %
b0001111011 &
1(
b0001111011 +
b0001111011 ,
#246000000
0!
0(
#247000000
1!
b0001111100 %
b0001111100 &
1(
b0001111100 +
b0001111100 ,
#248000000
0!
0(
#249000000
1!
b0001111101 %
b0001111101 &
1(
b0001111101 +
b0001111101 ,
#250000000
0!
0(
#251000000
1!
b0001111110 %
b0001111110 &
1(
b0001111110 +
b0001111110 ,
#252000000
0!
0(
#253000000
1!
b0001111111 %
b0001111111 &
1(
b0001111111 +
b0001111111 ,
#254000000
0!
0(
#255000000
1!
b0010000000 %
b0010000000 &
1(
b0010000000 +
b0010000000 ,
#256000000
0!
0(
#257000000
1!
b0010000001 %
b0010000001 &
1(
b0010000001 +
b0010000001 ,
#258000000
0!
0(
#259000000
1!
b0010000010 %
b0010000010 &
1(
b0010000010 +
b0010000010 ,
#260000000
0!
0(
#261000000
1!
b0010000011 %
b0010000011 &
1(
b0010000011 +
b0010000011 ,
#262000000
0!
0(
#263000000
1!
b0010000100 %
b0010000100 &
1(
b0010000100 +
b0010000100 ,
#264000000
0!
0(
#265000000
1!
b0010000101 %
b0010000101 &
1(
b0010000101 +
b0010000101 ,
#266000000
0!
0(
#267000000
1!
b0010000110 %
b0010000110 &
1(
b0010000110 +
b0010000110 ,
#268000000
0!
0(
#269000000
1!
b0010000111 %
b0010000111 &
1(
b0010000111 +
b0010000111 ,
#270000000
0!
0(
#271000000
1!
b0010001000 %
b0010001000 &
1(
b0010001000 +
b0010001000 ,
#272000000
0!
0(
#273000000
1!
b0010001001 %
b0010001001 &
1(
b0010001001 +
b0010001001 ,
#274000000
0!
0(
#275000000
1!
b0010001010 %
b0010001010 &
1(
b0010001010 +
b0010001010 ,
#276000000
0!
0(
#277000000
1!
b0010001011 %
b0010001011 &
1(
b0010001011 +
b0010001011 ,
#278000000
0!
0(
#279000000
1!
b0010001100 %
b0010001100 &
1(
b0010001100 +
b0010001100 ,
#280000000
0!
0(
#281000000
1!
b0010001101 %
b0010001101 &
1(
b0010001101 +
b0010001101 ,
#282000000
0!
0(
#283000000
1!
b0010001110 %
b0010001110 &
1(
b0010001110 +
b0010001110 ,
#284000000
0!
0(
#285000000
1!
b0010001111 %
b0010001111 &
1(
b0010001111 +
b0010001111 ,
#286000000
0!
0(
#287000000
1!
b0010010000 %
b0010010000 &
1(
b0010010000 +
b0010010000 ,
#288000000
0!
0(
#289000000
1!
b0010010001 %
b0010010001 &
1(
b0010010001 +
b0010010001 ,
#290000000
0!
0(
#291000000
1!
b0010010010 %
b0010010010 &
1(
b0010010010 +
b0010010010 ,
#292000000
0!
0(
#293000000
1!
b0010010011 %
b0010010011 &
1(
b0010010011 +
b0010010011 ,
#294000000
0!
0(
#295000000
1!
b0010010100 %
b0010010100 &
1(
b0010010100 +
b0010010100 ,
#296000000
0!
0(
#297000000
1!
b0010010101 %
b0010010101 &
1(
b0010010101 +
b0010010101 ,
#298000000
0!
0(
#299000000
1!
b0010010110 %
b0010010110 &
1(
b0010010110 +
b0010010110 ,
#300000000
0!
0(
#301000000
1!
b0010010111 %
b0010010111 &
1(
b0010010111 +
b0010010111 ,
#302000000
0!
0(
#303000000
1!
b0010011000 %
b0010011000 &
1(
b0010011000 +
b0010011000 ,
#304000000
0!
0(
#305000000
1!
b0010011001 %
b0010011001 &
1(
b0010011001 +
b0010011001 ,
#306000000
0!
0(
#307000000
1!
b0010011010 %
b0010011010 &
1(
b0010011010 +
b0010011010 ,
#308000000
0!
0(
#309000000
1!
b0010011011 %
b0010011011 &
1(
b0010011011 +
b0010011011 ,
#310000000
0!
0(
#311000000
1!
b0010011100 %
b0010011100 &
1(
b0010011100 +
b0010011100 ,
#312000000
0!
0(
#313000000
1!
b0010011101 %
b0010011101 &
1(
b0010011101 +
b0010011101 ,
#314000000
0!
0(
#315000000
1!
b0010011110 %
b0010011110 &
1(
b0010011110 +
b0010011110 ,
#316000000
0!
0(
#317000000
1!
b0010011111 %
b0010011111 &
1(
b0010011111 +
b0010011111 ,
#318000000
0!
0(
#319000000
1!
b0010100000 %
b0010100000 &
1(
b0010100000 +
b0010100000 ,
#320000000
0!
0(
#321000000
1!
b0010100001 %
b0010100001 &
1(
b0010100001 +
b0010100001 ,
#322000000
0!
0(
#323000000
1!
b0010100010 %
b0010100010 &
1(
b0010100010 +
b0010100010 ,
#324000000
0!
0(
#325000000
1!
b0010100011 %
b0010100011 &
1(
b0010100011 +
b0010100011 ,
#326000000
0!
0(
#327000000
1!
b0010100100 %
b0010100100 &
1(
b0010100100 +
b0010100100 ,
#328000000
0!
0(
#329000000
1!
b0010100101 %
b0010100101 &
1(
b0010100101 +
b0010100101 ,
#330000000
0!
0(
#331000000
1!
b0010100110 %
b0010100110 &
1(
b0010100110 +
b0010100110 ,
#332000000
0!
0(
#333000000
1!
b0010100111 %
b0010100111 &
1(
b0010100111 +
b0010100111 ,
#334000000
0!
0(
#335000000
1!
b0010101000 %
b0010101000 &
1(
b0010101000 +
b0010101000 ,
#336000000
0!
0(
#337000000
1!
b0010101001 %
b0010101001 &
1(
b0010101001 +
b0010101001 ,
#338000000
0!
0(
#339000000
1!
b0010101010 %
b0010101010 &
1(
b0010101010 +
b0010101010 ,
#340000000
0!
0(
#341000000
1!
b0010101011 %
b0010101011 &
1(
b0010101011 +
b0010101011 ,
#342000000
0!
0(
#343000000
1!
b0010101100 %
b0010101100 &
1(
b0010101100 +
b0010101100 ,
#344000000
0!
0(
#345000000
1!
b0010101101 %
b0010101101 &
1(
b0010101101 +
b0010101101 ,
#346000000
0!
0(
#347000000
1!
b0010101110 %
b0010101110 &
1(
b0010101110 +
b0010101110 ,
#348000000
0!
0(
#349000000
1!
b0010101111 %
b0010101111 &
1(
b0010101111 +
b0010101111 ,
#350000000
0!
0(
#351000000
1!
b0010110000 %
b0010110000 &
1(
b0010110000 +
b0010110000 ,
#352000000
0!
0(
#353000000
1!
b0010110001 %
b0010110001 &
1(
b0010110001 +
b0010110001 ,
#354000000
0!
0(
#355000000
1!
b0010110010 %
b0010110010 &
1(
b0010110010 +
b0010110010 ,
#356000000
0!
0(
#357000000
1!
b0010110011 %
b0010110011 &
1(
b0010110011 +
b0010110011 ,
#358000000
0!
0(
#359000000
1!
b0010110100 %
b0010110100 &
1(
b0010110100 +
b0010110100 ,
#360000000
0!
0(
#361000000
1!
b0010110101 %
b0010110101 &
1(
b0010110101 +
b0010110101 ,
#362000000
0!
0(
#363000000
1!
b0010110110 %
b0010110110 &
1(
b0010110110 +
b0010110110 ,
#364000000
0!
0(
#365000000
1!
b0010110111 %
b0010110111 &
1(
b0010110111 +
b0010110111 ,
#366000000
0!
0(
#367000000
1!
b0010111000 %
b0010111000 &
1(
b0010111000 +
b0010111000 ,
#368000000
0!
0(
#369000000
1!
b0010111001 %
b0010111001 &
1(
b0010111001 +
b0010111001 ,
#370000000
0!
0(
#371000000
1!
b0010111010 %
b0010111010 &
1(
b0010111010 +
b0010111010 ,
#372000000
0!
0(
#373000000
1!
b0010111011 %
b0010111011 &
1(
b0010111011 +
b0010111011 ,
#374000000
0!
0(
#375000000
1!
b0010111100 %
b0010111100 &
1(
b0010111100 +
b0010111100 ,
#376000000
0!
0(
#377000000
1!
b0010111101 %
b0010111101 &
1(
b0010111101 +
b0010111101 ,
#378000000
0!
0(
#379000000
1!
b0010111110 %
b0010111110 &
1(
b0010111110 +
b0010111110 ,
#380000000
0!
0(
#381000000
1!
b0010111111 %
b0010111111 &
1(
b0010111111 +
b0010111111 ,
#382000000
0!
0(
#383000000
1!
b0011000000 %
b0011000000 &
1(
b0011000000 +
b0011000000 ,
#384000000
0!
0(
#385000000
1!
b0011000001 %
b0011000001 &
1(
b0011000001 +
b0011000001 ,
#386000000
0!
0(
#387000000
1!
b0011000010 %
b0011000010 &
1(
b0011000010 +
b0011000010 ,
#388000000
0!
0(
#389000000
1!
b0011000011 %
b0011000011 &
1(
b0011000011 +
b0011000011 ,
#390000000
0!
0(
#391000000
1!
b0011000100 %
b0011000100 &
1(
b0011000100 +
b0011000100 ,
#392000000
0!
0(
#393000000
1!
b0011000101 %
b0011000101 &
1(
b0011000101 +
b0011000101 ,
#394000000
0!
0(
#395000000
1!
b0011000110 %
b0011000110 &
1(
b0011000110 +
b0011000110 ,
#396000000
0!
0(
#397000000
1!
b0011000111 %
b0011000111 &
1(
b0011000111 +
b0011000111 ,
#398000000
0!
0(
#399000000
1!
b0011001000 %
b0011001000 &
1(
b0011001000 +
b0011001000 ,
#400000000
0!
0(
#401000000
1!
b0011001001 %
b0011001001 &
1(
b0011001001 +
b0011001001 ,
#402000000
0!
0(
#403000000
1!
b0011001010 %
b0011001010 &
1(
b0011001010 +
b0011001010 ,
#404000000
0!
0(
#405000000
1!
b0011001011 %
b0011001011 &
1(
b0011001011 +
b0011001011 ,
#406000000
0!
0(
#407000000
1!
b0011001100 %
b0011001100 &
1(
b0011001100 +
b0011001100 ,
#408000000
0!
0(
#409000000
1!
b0011001101 %
b0011001101 &
1(
b0011001101 +
b0011001101 ,
#410000000
0!
0(
#411000000
1!
b0011001110 %
b0011001110 &
1(
b0011001110 +
b0011001110 ,
#412000000
0!
0(
#413000000
1!
b0011001111 %
b0011001111 &
1(
b0011001111 +
b0011001111 ,
#414000000
0!
0(
#415000000
1!
b0011010000 %
b0011010000 &
1(
b0011010000 +
b0011010000 ,
#416000000
0!
0(
#417000000
1!
b0011010001 %
b0011010001 &
1(
b0011010001 +
b0011010001 ,
#418000000
0!
0(
#419000000
1!
b0011010010 %
b0011010010 &
1(
b0011010010 +
b0011010010 ,
#420000000
0!
0(
#421000000
1!
b0011010011 %
b0011010011 &
1(
b0011010011 +
b0011010011 ,
#422000000
0!
0(
#423000000
1!
b0011010100 %
b0011010100 &
1(
b0011010100 +
b0011010100 ,
#424000000
0!
0(
#425000000
1!
b0011010101 %
b0011010101 &
1(
b0011010101 +
b0011010101 ,
#426000000
0!
0(
#427000000
1!
b0011010110 %
b0011010110 &
1(
b0011010110 +
b0011010110 ,
#428000000
0!
0(
#429000000
1!
b0011010111 %
b0011010111 &
1(
b0011010111 +
b0011010111 ,
#430000000
0!
0(
#431000000
1!
b0011011000 %
b0011011000 &
1(
b0011011000 +
b0011011000 ,
#432000000
0!
0(
#433000000
1!
b0011011001 %
b0011011001 &
1(
b0011011001 +
b0011011001 ,
#434000000
0!
0(
#435000000
1!
b0011011010 %
b0011011010 &
1(
b0011011010 +
b0011011010 ,
#436000000
0!
0(
#437000000
1!
b0011011011 %
b0011011011 &
1(
b0011011011 +
b0011011011 ,
#438000000
0!
0(
#439000000
1!
b0011011100 %
b0011011100 &
1(
b0011011100 +
b0011011100 ,
#440000000
0!
0(
#441000000
1!
b0011011101 %
b0011011101 &
1(
b0011011101 +
b0011011101 ,
#442000000
0!
0(
#443000000
1!
b0011011110 %
b0011011110 &
1(
b0011011110 +
b0011011110 ,
#444000000
0!
0(
#445000000
1!
b0011011111 %
b0011011111 &
1(
b0011011111 +
b0011011111 ,
#446000000
0!
0(
#447000000
1!
b0011100000 %
b0011100000 &
1(
b0011100000 +
b0011100000 ,
#448000000
0!
0(
#449000000
1!
b0011100001 %
b0011100001 &
1(
b0011100001 +
b0011100001 ,
#450000000
0!
0(
#451000000
1!
b0011100010 %
b0011100010 &
1(
b0011100010 +
b0011100010 ,
#452000000
0!
0(
#453000000
1!
b0011100011 %
b0011100011 &
1(
b0011100011 +
b0011100011 ,
#454000000
0!
0(
#455000000
1!
b0011100100 %
b0011100100 &
1(
b0011100100 +
b0011100100 ,
#456000000
0!
0(
#457000000
1!
b0011100101 %
b0011100101 &
1(
b0011100101 +
b0011100101 ,
#458000000
0!
0(
#459000000
1!
b0011100110 %
b0011100110 &
1(
b0011100110 +
b0011100110 ,
#460000000
0!
0(
#461000000
1!
b0011100111 %
b0011100111 &
1(
b0011100111 +
b0011100111 ,
#462000000
0!
0(
#463000000
1!
b0011101000 %
b0011101000 &
1(
b0011101000 +
b0011101000 ,
#464000000
0!
0(
#465000000
1!
b0011101001 %
b0011101001 &
1(
b0011101001 +
b0011101001 ,
#466000000
0!
0(
#467000000
1!
b0011101010 %
b0011101010 &
1(
b0011101010 +
b0011101010 ,
#468000000
0!
0(
#469000000
1!
b0011101011 %
b0011101011 &
1(
b0011101011 +
b0011101011 ,
#470000000
0!
0(
#471000000
1!
b0011101100 %
b0011101100 &
1(
b0011101100 +
b0011101100 ,
#472000000
0!
0(
#473000000
1!
b0011101101 %
b0011101101 &
1(
b0011101101 +
b0011101101 ,
#474000000
0!
0(
#475000000
1!
b0011101110 %
b0011101110 &
1(
b0011101110 +
b0011101110 ,
#476000000
0!
0(
#477000000
1!
b0011101111 %
b0011101111 &
1(
b0011101111 +
b0011101111 ,
#478000000
0!
0(
#479000000
1!
b0011110000 %
b0011110000 &
1(
b0011110000 +
b0011110000 ,
#480000000
0!
0(
#481000000
1!
b0011110001 %
b0011110001 &
1(
b0011110001 +
b0011110001 ,
#482000000
0!
0(
#483000000
1!
b0011110010 %
b0011110010 &
1(
b0011110010 +
b0011110010 ,
#484000000
0!
0(
#485000000
1!
b0011110011 %
b0011110011 &
1(
b0011110011 +
b0011110011 ,
#486000000
0!
0(
#487000000
1!
b0011110100 %
b0011110100 &
1(
b0011110100 +
b0011110100 ,
#488000000
0!
0(
#489000000
1!
b0011110101 %
b0011110101 &
1(
b0011110101 +
b0011110101 ,
#490000000
0!
0(
